{
  "user_id": 2,
  "template_file_path": "C:\\Users\\57189\\dhu-journal-app\\backend\\user_configs\\user_2\\stats_template_20251114_232204.xlsx",
  "column_mapping": [
    {
      "system_key": "manuscript_id",
      "template_header": "稿件",
      "order": 1,
      "is_custom": false
    },
    {
      "system_key": "pdf_pages",
      "template_header": "页数",
      "order": 2,
      "is_custom": false
    },
    {
      "system_key": "first_author",
      "template_header": "一作",
      "order": 3,
      "is_custom": false
    },
    {
      "system_key": "123",
      "template_header": "123",
      "order": 4,
      "is_custom": true
    }
  ],
  "created_at": "2025-11-14T23:22:04.054430",
  "updated_at": "2025-11-14T23:22:04.054430"
}